{
  "HALProvider": {
    "Other Devices": {
      "RelativeEncoder[1]": {
        "header": {
          "open": true
        }
      },
      "SparkMax[1]": {
        "header": {
          "open": true
        }
      },
      "SparkMax[2]": {
        "header": {
          "open": true
        }
      },
      "SparkMax[3]": {
        "header": {
          "open": true
        }
      },
      "SparkMax[4]": {
        "header": {
          "open": true
        }
      },
      "SparkMax[5]": {
        "header": {
          "open": true
        }
      }
    }
  },
  "NTProvider": {
    "types": {
      "/FMSInfo": "FMSInfo"
    }
  }
}
